zakka/__init__.py
zakka/permissions.py
zakka/test.py
zakka/contrib/__init__.py
zakka/contrib/decorators.py
zakka/contrib/celery/__init__.py
zakka/contrib/celery/decorators.py
zakka/contrib/celery/views.py
zakka/contrib/celery/management/__init__.py
zakka/contrib/celery/management/commands/__init__.py
zakka/contrib/celery/management/commands/tasks.py
zakka/contrib/utils/__init__.py
zakka/contrib/utils/templatetags/__init__.py
zakka/contrib/utils/templatetags/zakka.py
zakka/http/__init__.py
zakka/http/auth.py
zakka/http/client.py
zakka/mixins/__init__.py
zakka/mixins/command.py
django_zakka-0.7.0.dist-info/METADATA
django_zakka-0.7.0.dist-info/WHEEL
django_zakka-0.7.0.dist-info/top_level.txt
django_zakka-0.7.0.dist-info/RECORD
