Metadata-Version: 2.4
Name: django-zakka
Version: 0.7.0
Author: Paul Traylor
License: MIT License
Project-URL: Issues, http://github.com/kfdm/django-zakka/issues
Project-URL: Source Code, http://github.com/kfdm/django-zakka
Keywords: django
Classifier: Environment :: Web Environment
Classifier: Framework :: Django :: 3.2
Classifier: Framework :: Django
Classifier: Intended Audience :: Developers
Classifier: License :: OSI Approved :: MIT License
Classifier: Operating System :: OS Independent
Classifier: Programming Language :: Python :: 3
Classifier: Programming Language :: Python :: 3.9
Classifier: Programming Language :: Python
Classifier: Topic :: Internet :: WWW/HTTP :: Dynamic Content
Classifier: Topic :: Internet :: WWW/HTTP
Requires-Python: >=3.9
Requires-Dist: Django>=3.2
Requires-Dist: importlib-metadata>=1.0; python_version < "3.8"
Provides-Extra: requests
Requires-Dist: requests; extra == "requests"
